{
    "Name": "Microsoft.JScript.Vsa",
    "Version": "1.0.0",
    "Packages": {
        "Type": "SDK",
        "Name": "Microsoft.JScript.Vsa"
    },
    "Recommendations": [
        {
            "Type": "Method",
            "Value": "Microsoft.JScript.Vsa.BaseVsaSite.Notify(string, object)",
            "Name": "Notify",
            "KeyType": "",
            "RecommendedActions": [
                {
                    "Source": "Amazon",
                    "Preferred": "yes",
                    "TargetFrameworks": [
                        "netcoreapp3.1"
                    ],
                    "Description": "JScript won't be ported to .NET Core. See https://aka.ms/unsupported-netfx-api.",
                    "Actions": []
                }
            ]
        },
        {
            "Type": "Method",
            "Value": "Microsoft.JScript.Vsa.BaseVsaEngine.get_Version()",
            "Name": "get_Version",
            "KeyType": "",
            "RecommendedActions": [
                {
                    "Source": "Amazon",
                    "Preferred": "yes",
                    "TargetFrameworks": [
                        "netcoreapp3.1"
                    ],
                    "Description": "JScript won't be ported to .NET Core. See https://aka.ms/unsupported-netfx-api.",
                    "Actions": []
                }
            ]
        },
        {
            "Type": "Method",
            "Value": "Microsoft.JScript.Vsa.IJSVsaCodeItem.set_SourceText(string)",
            "Name": "set_SourceText",
            "KeyType": "",
            "RecommendedActions": [
                {
                    "Source": "Amazon",
                    "Preferred": "yes",
                    "TargetFrameworks": [
                        "netcoreapp3.1"
                    ],
                    "Description": "JScript won't be ported to .NET Core. See https://aka.ms/unsupported-netfx-api.",
                    "Actions": []
                }
            ]
        },
        {
            "Type": "Method",
            "Value": "Microsoft.JScript.Vsa.BaseVsaEngine.Preconditions(Microsoft.JScript.Vsa.BaseVsaEngine.Pre)",
            "Name": "Preconditions",
            "KeyType": "",
            "RecommendedActions": [
                {
                    "Source": "Amazon",
                    "Preferred": "yes",
                    "TargetFrameworks": [
                        "netcoreapp3.1"
                    ],
                    "Description": "JScript won't be ported to .NET Core. See https://aka.ms/unsupported-netfx-api.",
                    "Actions": []
                }
            ]
        },
        {
            "Type": "Method",
            "Value": "Microsoft.JScript.Vsa.IJSVsaItems.CreateItem(string, Microsoft.JScript.Vsa.JSVsaItemType, Microsoft.JScript.Vsa.JSVsaItemFlag)",
            "Name": "CreateItem",
            "KeyType": "",
            "RecommendedActions": [
                {
                    "Source": "Amazon",
                    "Preferred": "yes",
                    "TargetFrameworks": [
                        "netcoreapp3.1"
                    ],
                    "Description": "JScript won't be ported to .NET Core. See https://aka.ms/unsupported-netfx-api.",
                    "Actions": []
                }
            ]
        },
        {
            "Type": "Method",
            "Value": "Microsoft.JScript.Vsa.BaseVsaEngine.set_AppDomain(System._AppDomain)",
            "Name": "set_AppDomain",
            "KeyType": "",
            "RecommendedActions": [
                {
                    "Source": "Amazon",
                    "Preferred": "yes",
                    "TargetFrameworks": [
                        "netcoreapp3.1"
                    ],
                    "Description": "JScript won't be ported to .NET Core. See https://aka.ms/unsupported-netfx-api.",
                    "Actions": []
                }
            ]
        },
        {
            "Type": "Method",
            "Value": "Microsoft.JScript.Vsa.IJSVsaItems.get_Item(string)",
            "Name": "get_Item",
            "KeyType": "",
            "RecommendedActions": [
                {
                    "Source": "Amazon",
                    "Preferred": "yes",
                    "TargetFrameworks": [
                        "netcoreapp3.1"
                    ],
                    "Description": "JScript won't be ported to .NET Core. See https://aka.ms/unsupported-netfx-api.",
                    "Actions": []
                }
            ]
        },
        {
            "Type": "Method",
            "Value": "Microsoft.JScript.Vsa.BaseVsaEngine.get_AppDomain()",
            "Name": "get_AppDomain",
            "KeyType": "",
            "RecommendedActions": [
                {
                    "Source": "Amazon",
                    "Preferred": "yes",
                    "TargetFrameworks": [
                        "netcoreapp3.1"
                    ],
                    "Description": "JScript won't be ported to .NET Core. See https://aka.ms/unsupported-netfx-api.",
                    "Actions": []
                }
            ]
        },
        {
            "Type": "Method",
            "Value": "Microsoft.JScript.Vsa.ResInfo.ResInfo(string, bool)",
            "Name": ".ctor",
            "KeyType": "",
            "RecommendedActions": [
                {
                    "Source": "Amazon",
                    "Preferred": "yes",
                    "TargetFrameworks": [
                        "netcoreapp3.1"
                    ],
                    "Description": "JScript won't be ported to .NET Core. See https://aka.ms/unsupported-netfx-api.",
                    "Actions": []
                }
            ]
        },
        {
            "Type": "Method",
            "Value": "Microsoft.JScript.Vsa.IJSVsaGlobalItem.ExposeMembers.get_ExposeMembers()",
            "Name": "get_ExposeMembers",
            "KeyType": "",
            "RecommendedActions": [
                {
                    "Source": "Amazon",
                    "Preferred": "yes",
                    "TargetFrameworks": [
                        "netcoreapp3.1"
                    ],
                    "Description": "JScript won't be ported to .NET Core. See https://aka.ms/unsupported-netfx-api.",
                    "Actions": []
                }
            ]
        },
        {
            "Type": "Method",
            "Value": "Microsoft.JScript.Vsa.IJSVsaItems.get_Item(int)",
            "Name": "get_Item",
            "KeyType": "",
            "RecommendedActions": [
                {
                    "Source": "Amazon",
                    "Preferred": "yes",
                    "TargetFrameworks": [
                        "netcoreapp3.1"
                    ],
                    "Description": "JScript won't be ported to .NET Core. See https://aka.ms/unsupported-netfx-api.",
                    "Actions": []
                }
            ]
        },
        {
            "Type": "Method",
            "Value": "Microsoft.JScript.Vsa.IJSVsaError.get_Description()",
            "Name": "get_Description",
            "KeyType": "",
            "RecommendedActions": [
                {
                    "Source": "Amazon",
                    "Preferred": "yes",
                    "TargetFrameworks": [
                        "netcoreapp3.1"
                    ],
                    "Description": "JScript won't be ported to .NET Core. See https://aka.ms/unsupported-netfx-api.",
                    "Actions": []
                }
            ]
        },
        {
            "Type": "Method",
            "Value": "Microsoft.JScript.Vsa.VsaEngine.RegisterEventSource(string)",
            "Name": "RegisterEventSource",
            "KeyType": "",
            "RecommendedActions": [
                {
                    "Source": "Amazon",
                    "Preferred": "yes",
                    "TargetFrameworks": [
                        "netcoreapp3.1"
                    ],
                    "Description": "JScript won't be ported to .NET Core. See https://aka.ms/unsupported-netfx-api.",
                    "Actions": []
                }
            ]
        },
        {
            "Type": "Method",
            "Value": "Microsoft.JScript.Vsa.BaseVsaEngine.SetCustomOption(string, object)",
            "Name": "SetCustomOption",
            "KeyType": "",
            "RecommendedActions": [
                {
                    "Source": "Amazon",
                    "Preferred": "yes",
                    "TargetFrameworks": [
                        "netcoreapp3.1"
                    ],
                    "Description": "JScript won't be ported to .NET Core. See https://aka.ms/unsupported-netfx-api.",
                    "Actions": []
                }
            ]
        },
        {
            "Type": "Method",
            "Value": "Microsoft.JScript.Vsa.JSVsaException.JSVsaException()",
            "Name": ".ctor",
            "KeyType": "",
            "RecommendedActions": [
                {
                    "Source": "Amazon",
                    "Preferred": "yes",
                    "TargetFrameworks": [
                        "netcoreapp3.1"
                    ],
                    "Description": "JScript won't be ported to .NET Core. See https://aka.ms/unsupported-netfx-api.",
                    "Actions": []
                }
            ]
        },
        {
            "Type": "Method",
            "Value": "Microsoft.JScript.Vsa.IJSVsaCodeItem.AppendSourceText(string)",
            "Name": "AppendSourceText",
            "KeyType": "",
            "RecommendedActions": [
                {
                    "Source": "Amazon",
                    "Preferred": "yes",
                    "TargetFrameworks": [
                        "netcoreapp3.1"
                    ],
                    "Description": "JScript won't be ported to .NET Core. See https://aka.ms/unsupported-netfx-api.",
                    "Actions": []
                }
            ]
        },
        {
            "Type": "Method",
            "Value": "Microsoft.JScript.Vsa.VsaEngine.CreateEngineWithType(System.RuntimeTypeHandle)",
            "Name": "CreateEngineWithType",
            "KeyType": "",
            "RecommendedActions": [
                {
                    "Source": "Amazon",
                    "Preferred": "yes",
                    "TargetFrameworks": [
                        "netcoreapp3.1"
                    ],
                    "Description": "JScript won't be ported to .NET Core. See https://aka.ms/unsupported-netfx-api.",
                    "Actions": []
                }
            ]
        },
        {
            "Type": "Namespace",
            "Value": "Microsoft.JScript.Vsa",
            "Name": "Microsoft.JScript.Vsa",
            "KeyType": "",
            "RecommendedActions": [
                {
                    "Source": "Amazon",
                    "Preferred": "yes",
                    "TargetFrameworks": [
                        "netcoreapp3.1"
                    ],
                    "Description": "JScript won't be ported to .NET Core. See https://aka.ms/unsupported-netfx-api.",
                    "Actions": []
                }
            ]
        },
        {
            "Type": "Method",
            "Value": "Microsoft.JScript.Vsa.IJSVsaError.get_Line()",
            "Name": "get_Line",
            "KeyType": "",
            "RecommendedActions": [
                {
                    "Source": "Amazon",
                    "Preferred": "yes",
                    "TargetFrameworks": [
                        "netcoreapp3.1"
                    ],
                    "Description": "JScript won't be ported to .NET Core. See https://aka.ms/unsupported-netfx-api.",
                    "Actions": []
                }
            ]
        },
        {
            "Type": "Method",
            "Value": "Microsoft.JScript.Vsa.VsaEngine.Clone(System.AppDomain)",
            "Name": "Clone",
            "KeyType": "",
            "RecommendedActions": [
                {
                    "Source": "Amazon",
                    "Preferred": "yes",
                    "TargetFrameworks": [
                        "netcoreapp3.1"
                    ],
                    "Description": "JScript won't be ported to .NET Core. See https://aka.ms/unsupported-netfx-api.",
                    "Actions": []
                }
            ]
        },
        {
            "Type": "Method",
            "Value": "Microsoft.JScript.Vsa.IJSVsaCodeItem.RemoveEventSource(string)",
            "Name": "RemoveEventSource",
            "KeyType": "",
            "RecommendedActions": [
                {
                    "Source": "Amazon",
                    "Preferred": "yes",
                    "TargetFrameworks": [
                        "netcoreapp3.1"
                    ],
                    "Description": "JScript won't be ported to .NET Core. See https://aka.ms/unsupported-netfx-api.",
                    "Actions": []
                }
            ]
        },
        {
            "Type": "Method",
            "Value": "Microsoft.JScript.Vsa.VsaEngine.ConnectEvents()",
            "Name": "ConnectEvents",
            "KeyType": "",
            "RecommendedActions": [
                {
                    "Source": "Amazon",
                    "Preferred": "yes",
                    "TargetFrameworks": [
                        "netcoreapp3.1"
                    ],
                    "Description": "JScript won't be ported to .NET Core. See https://aka.ms/unsupported-netfx-api.",
                    "Actions": []
                }
            ]
        },
        {
            "Type": "Method",
            "Value": "Microsoft.JScript.Vsa.BaseVsaEngine.SetOption(string, object)",
            "Name": "SetOption",
            "KeyType": "",
            "RecommendedActions": [
                {
                    "Source": "Amazon",
                    "Preferred": "yes",
                    "TargetFrameworks": [
                        "netcoreapp3.1"
                    ],
                    "Description": "JScript won't be ported to .NET Core. See https://aka.ms/unsupported-netfx-api.",
                    "Actions": []
                }
            ]
        },
        {
            "Type": "Method",
            "Value": "Microsoft.JScript.Vsa.IJSVsaReferenceItem.AssemblyName.set_AssemblyName(string)",
            "Name": "set_AssemblyName",
            "KeyType": "",
            "RecommendedActions": [
                {
                    "Source": "Amazon",
                    "Preferred": "yes",
                    "TargetFrameworks": [
                        "netcoreapp3.1"
                    ],
                    "Description": "JScript won't be ported to .NET Core. See https://aka.ms/unsupported-netfx-api.",
                    "Actions": []
                }
            ]
        },
        {
            "Type": "Method",
            "Value": "Microsoft.JScript.Vsa.BaseVsaEngine.get_Assembly()",
            "Name": "get_Assembly",
            "KeyType": "",
            "RecommendedActions": [
                {
                    "Source": "Amazon",
                    "Preferred": "yes",
                    "TargetFrameworks": [
                        "netcoreapp3.1"
                    ],
                    "Description": "JScript won't be ported to .NET Core. See https://aka.ms/unsupported-netfx-api.",
                    "Actions": []
                }
            ]
        },
        {
            "Type": "Method",
            "Value": "Microsoft.JScript.Vsa.IJSVsaSite.GetCompiledState(byte[], byte[])",
            "Name": "GetCompiledState",
            "KeyType": "",
            "RecommendedActions": [
                {
                    "Source": "Amazon",
                    "Preferred": "yes",
                    "TargetFrameworks": [
                        "netcoreapp3.1"
                    ],
                    "Description": "JScript won't be ported to .NET Core. See https://aka.ms/unsupported-netfx-api.",
                    "Actions": []
                }
            ]
        },
        {
            "Type": "Method",
            "Value": "Microsoft.JScript.Vsa.IJSVsaEngine.IsValidIdentifier(string)",
            "Name": "IsValidIdentifier",
            "KeyType": "",
            "RecommendedActions": [
                {
                    "Source": "Amazon",
                    "Preferred": "yes",
                    "TargetFrameworks": [
                        "netcoreapp3.1"
                    ],
                    "Description": "JScript won't be ported to .NET Core. See https://aka.ms/unsupported-netfx-api.",
                    "Actions": []
                }
            ]
        },
        {
            "Type": "Method",
            "Value": "Microsoft.JScript.Vsa.VsaEngine.SetOption(string, object)",
            "Name": "SetOption",
            "KeyType": "",
            "RecommendedActions": [
                {
                    "Source": "Amazon",
                    "Preferred": "yes",
                    "TargetFrameworks": [
                        "netcoreapp3.1"
                    ],
                    "Description": "JScript won't be ported to .NET Core. See https://aka.ms/unsupported-netfx-api.",
                    "Actions": []
                }
            ]
        },
        {
            "Type": "Method",
            "Value": "Microsoft.JScript.Vsa.IJSVsaError.get_SourceMoniker()",
            "Name": "get_SourceMoniker",
            "KeyType": "",
            "RecommendedActions": [
                {
                    "Source": "Amazon",
                    "Preferred": "yes",
                    "TargetFrameworks": [
                        "netcoreapp3.1"
                    ],
                    "Description": "JScript won't be ported to .NET Core. See https://aka.ms/unsupported-netfx-api.",
                    "Actions": []
                }
            ]
        },
        {
            "Type": "Method",
            "Value": "Microsoft.JScript.Vsa.VsaEngine.GetGlobalScope()",
            "Name": "GetGlobalScope",
            "KeyType": "",
            "RecommendedActions": [
                {
                    "Source": "Amazon",
                    "Preferred": "yes",
                    "TargetFrameworks": [
                        "netcoreapp3.1"
                    ],
                    "Description": "JScript won't be ported to .NET Core. See https://aka.ms/unsupported-netfx-api.",
                    "Actions": []
                }
            ]
        },
        {
            "Type": "Method",
            "Value": "Microsoft.JScript.Vsa.IJSVsaItem.Name.set_Name(string)",
            "Name": "set_Name",
            "KeyType": "",
            "RecommendedActions": [
                {
                    "Source": "Amazon",
                    "Preferred": "yes",
                    "TargetFrameworks": [
                        "netcoreapp3.1"
                    ],
                    "Description": "JScript won't be ported to .NET Core. See https://aka.ms/unsupported-netfx-api.",
                    "Actions": []
                }
            ]
        },
        {
            "Type": "Method",
            "Value": "Microsoft.JScript.Vsa.IJSVsaEngine.set_Name(string)",
            "Name": "set_Name",
            "KeyType": "",
            "RecommendedActions": [
                {
                    "Source": "Amazon",
                    "Preferred": "yes",
                    "TargetFrameworks": [
                        "netcoreapp3.1"
                    ],
                    "Description": "JScript won't be ported to .NET Core. See https://aka.ms/unsupported-netfx-api.",
                    "Actions": []
                }
            ]
        },
        {
            "Type": "Method",
            "Value": "Microsoft.JScript.Vsa.VsaEngine.VsaEngine(bool)",
            "Name": ".ctor",
            "KeyType": "",
            "RecommendedActions": [
                {
                    "Source": "Amazon",
                    "Preferred": "yes",
                    "TargetFrameworks": [
                        "netcoreapp3.1"
                    ],
                    "Description": "JScript won't be ported to .NET Core. See https://aka.ms/unsupported-netfx-api.",
                    "Actions": []
                }
            ]
        },
        {
            "Type": "Method",
            "Value": "Microsoft.JScript.Vsa.BaseVsaEngine.Reset()",
            "Name": "Reset",
            "KeyType": "",
            "RecommendedActions": [
                {
                    "Source": "Amazon",
                    "Preferred": "yes",
                    "TargetFrameworks": [
                        "netcoreapp3.1"
                    ],
                    "Description": "JScript won't be ported to .NET Core. See https://aka.ms/unsupported-netfx-api.",
                    "Actions": []
                }
            ]
        },
        {
            "Type": "Method",
            "Value": "Microsoft.JScript.Vsa.JSVsaException.JSVsaException(Microsoft.JScript.Vsa.JSVsaError, string)",
            "Name": ".ctor",
            "KeyType": "",
            "RecommendedActions": [
                {
                    "Source": "Amazon",
                    "Preferred": "yes",
                    "TargetFrameworks": [
                        "netcoreapp3.1"
                    ],
                    "Description": "JScript won't be ported to .NET Core. See https://aka.ms/unsupported-netfx-api.",
                    "Actions": []
                }
            ]
        }
    ]
}