{
  "Name": "Microsoft.Activities.Build.Expressions",
  "Version": "1.0.0",
  "Packages": [
    {
      "Name": "Microsoft.Activities.Build.Expressions",
      "Type": "SDK"
    }
  ],
  "Recommendations": [
    {
      "Type": "Method",
      "Name": "",
      "Value": "Microsoft.Activities.Build.Expressions.ExpressionsBuildExtension.Execute(Microsoft.Build.Tasks.Xaml.XamlBuildTypeInspectionExtensionContext)",
      "KeyType": "",
      "RecommendedActions": [
        {
          "Source": "Amazon",
          "Preferred": "yes",
          "TargetFrameworks": [
            "netcoreapp3.1"
          ],
          "Description": "Windows Workflow Foundation (WF) won't be ported to .NET Core. See https://aka.ms/unsupported-netfx-api.",
          "Actions": []
        }
      ]
    },
    {
      "Type": "Namespace",
      "Name": "",
      "Value": "Microsoft.Activities.Build.Expressions",
      "KeyType": "",
      "RecommendedActions": [
        {
          "Source": "Amazon",
          "Preferred": "yes",
          "TargetFrameworks": [
            "netcoreapp3.1"
          ],
          "Description": "Windows Workflow Foundation (WF) won't be ported to .NET Core. See https://aka.ms/unsupported-netfx-api.",
          "Actions": []
        }
      ]
    },
    {
      "Type": "Method",
      "Name": "",
      "Value": "Microsoft.Activities.Build.Expressions.ExpressionsBuildExtension.ExpressionsBuildExtension()",
      "KeyType": "",
      "RecommendedActions": [
        {
          "Source": "Amazon",
          "Preferred": "yes",
          "TargetFrameworks": [
            "netcoreapp3.1"
          ],
          "Description": "Windows Workflow Foundation (WF) won't be ported to .NET Core. See https://aka.ms/unsupported-netfx-api.",
          "Actions": []
        }
      ]
    }
  ]
}