{
    "Name": "System.Runtime.Remoting.Channels.Ipc",
    "Version": "1.0.0",
    "Packages": {
        "Type": "SDK",
        "Name": "System.Runtime.Remoting.Channels.Ipc"
    },
    "Recommendations": [
        {
            "Type": "Method",
            "Value": "System.Runtime.Remoting.Channels.Ipc.IpcChannel.get_IsSecured()",
            "Name": "get_IsSecured",
            "KeyType": "",
            "RecommendedActions": [
                {
                    "Source": "Amazon",
                    "Preferred": "yes",
                    "TargetFrameworks": [
                        "netcoreapp3.1"
                    ],
                    "Description": ".NET Remoting won't be ported to .NET Core. See https://aka.ms/unsupported-netfx-api.",
                    "Actions": []
                }
            ]
        },
        {
            "Type": "Method",
            "Value": "System.Runtime.Remoting.Channels.Ipc.IpcServerChannel.get_ChannelData()",
            "Name": "get_ChannelData",
            "KeyType": "",
            "RecommendedActions": [
                {
                    "Source": "Amazon",
                    "Preferred": "yes",
                    "TargetFrameworks": [
                        "netcoreapp3.1"
                    ],
                    "Description": ".NET Remoting won't be ported to .NET Core. See https://aka.ms/unsupported-netfx-api.",
                    "Actions": []
                }
            ]
        },
        {
            "Type": "Method",
            "Value": "System.Runtime.Remoting.Channels.Ipc.IpcChannel.IpcChannel(string)",
            "Name": ".ctor",
            "KeyType": "",
            "RecommendedActions": [
                {
                    "Source": "Amazon",
                    "Preferred": "yes",
                    "TargetFrameworks": [
                        "netcoreapp3.1"
                    ],
                    "Description": ".NET Remoting won't be ported to .NET Core. See https://aka.ms/unsupported-netfx-api.",
                    "Actions": []
                }
            ]
        },
        {
            "Type": "Method",
            "Value": "System.Runtime.Remoting.Channels.Ipc.IpcServerChannel.IpcServerChannel(string, string)",
            "Name": ".ctor",
            "KeyType": "",
            "RecommendedActions": [
                {
                    "Source": "Amazon",
                    "Preferred": "yes",
                    "TargetFrameworks": [
                        "netcoreapp3.1"
                    ],
                    "Description": ".NET Remoting won't be ported to .NET Core. See https://aka.ms/unsupported-netfx-api.",
                    "Actions": []
                }
            ]
        },
        {
            "Type": "Method",
            "Value": "System.Runtime.Remoting.Channels.Ipc.IpcClientChannel.get_ChannelPriority()",
            "Name": "get_ChannelPriority",
            "KeyType": "",
            "RecommendedActions": [
                {
                    "Source": "Amazon",
                    "Preferred": "yes",
                    "TargetFrameworks": [
                        "netcoreapp3.1"
                    ],
                    "Description": ".NET Remoting won't be ported to .NET Core. See https://aka.ms/unsupported-netfx-api.",
                    "Actions": []
                }
            ]
        },
        {
            "Type": "Method",
            "Value": "System.Runtime.Remoting.Channels.Ipc.IpcClientChannel.IpcClientChannel(System.Collections.IDictionary, System.Runtime.Remoting.Channels.IClientChannelSinkProvider)",
            "Name": ".ctor",
            "KeyType": "",
            "RecommendedActions": [
                {
                    "Source": "Amazon",
                    "Preferred": "yes",
                    "TargetFrameworks": [
                        "netcoreapp3.1"
                    ],
                    "Description": ".NET Remoting won't be ported to .NET Core. See https://aka.ms/unsupported-netfx-api.",
                    "Actions": []
                }
            ]
        },
        {
            "Type": "Namespace",
            "Value": "System.Runtime.Remoting.Channels.Ipc",
            "Name": "System.Runtime.Remoting.Channels.Ipc",
            "KeyType": "",
            "RecommendedActions": [
                {
                    "Source": "Amazon",
                    "Preferred": "yes",
                    "TargetFrameworks": [
                        "netcoreapp3.1"
                    ],
                    "Description": ".NET Remoting won't be ported to .NET Core. See https://aka.ms/unsupported-netfx-api.",
                    "Actions": []
                }
            ]
        },
        {
            "Type": "Method",
            "Value": "System.Runtime.Remoting.Channels.Ipc.IpcServerChannel.IpcServerChannel(string)",
            "Name": ".ctor",
            "KeyType": "",
            "RecommendedActions": [
                {
                    "Source": "Amazon",
                    "Preferred": "yes",
                    "TargetFrameworks": [
                        "netcoreapp3.1"
                    ],
                    "Description": ".NET Remoting won't be ported to .NET Core. See https://aka.ms/unsupported-netfx-api.",
                    "Actions": []
                }
            ]
        },
        {
            "Type": "Method",
            "Value": "System.Runtime.Remoting.Channels.Ipc.IpcServerChannel.GetUrlsForUri(string)",
            "Name": "GetUrlsForUri",
            "KeyType": "",
            "RecommendedActions": [
                {
                    "Source": "Amazon",
                    "Preferred": "yes",
                    "TargetFrameworks": [
                        "netcoreapp3.1"
                    ],
                    "Description": ".NET Remoting won't be ported to .NET Core. See https://aka.ms/unsupported-netfx-api.",
                    "Actions": []
                }
            ]
        }
    ]
}