{
    "Name": "System.Web.WebSockets",
    "Version": "1.0.0",
    "Packages": {
        "Type": "SDK",
        "Name": "System.Web.WebSockets"
    },
    "Recommendations": [
        {
            "Type": "Method",
            "Value": "System.Web.WebSockets.AspNetWebSocketContext.get_Cache()",
            "Name": "get_Cache",
            "KeyType": "",
            "RecommendedActions": [
                {
                    "Source": "Amazon",
                    "Preferred": "yes",
                    "TargetFrameworks": [
                        "netcoreapp3.1"
                    ],
                    "Description": "System.Web (AKA classic ASP.NET) won't be ported to .NET Core. See https://aka.ms/unsupported-netfx-api.",
                    "Actions": []
                }
            ]
        },
        {
            "Type": "Method",
            "Value": "System.Web.WebSockets.AspNetWebSocket.get_CloseStatus()",
            "Name": "get_CloseStatus",
            "KeyType": "",
            "RecommendedActions": [
                {
                    "Source": "Amazon",
                    "Preferred": "yes",
                    "TargetFrameworks": [
                        "netcoreapp3.1"
                    ],
                    "Description": "System.Web (AKA classic ASP.NET) won't be ported to .NET Core. See https://aka.ms/unsupported-netfx-api.",
                    "Actions": []
                }
            ]
        },
        {
            "Type": "Method",
            "Value": "System.Web.WebSockets.AspNetWebSocket.get_CloseStatusDescription()",
            "Name": "get_CloseStatusDescription",
            "KeyType": "",
            "RecommendedActions": [
                {
                    "Source": "Amazon",
                    "Preferred": "yes",
                    "TargetFrameworks": [
                        "netcoreapp3.1"
                    ],
                    "Description": "System.Web (AKA classic ASP.NET) won't be ported to .NET Core. See https://aka.ms/unsupported-netfx-api.",
                    "Actions": []
                }
            ]
        },
        {
            "Type": "Method",
            "Value": "System.Web.WebSockets.AspNetWebSocketContext.get_ServerVariables()",
            "Name": "get_ServerVariables",
            "KeyType": "",
            "RecommendedActions": [
                {
                    "Source": "Amazon",
                    "Preferred": "yes",
                    "TargetFrameworks": [
                        "netcoreapp3.1"
                    ],
                    "Description": "System.Web (AKA classic ASP.NET) won't be ported to .NET Core. See https://aka.ms/unsupported-netfx-api.",
                    "Actions": []
                }
            ]
        },
        {
            "Type": "Method",
            "Value": "System.Web.WebSockets.AspNetWebSocketOptions.get_SubProtocol()",
            "Name": "get_SubProtocol",
            "KeyType": "",
            "RecommendedActions": [
                {
                    "Source": "Amazon",
                    "Preferred": "yes",
                    "TargetFrameworks": [
                        "netcoreapp3.1"
                    ],
                    "Description": "System.Web (AKA classic ASP.NET) won't be ported to .NET Core. See https://aka.ms/unsupported-netfx-api.",
                    "Actions": []
                }
            ]
        },
        {
            "Type": "Method",
            "Value": "System.Web.WebSockets.AspNetWebSocketOptions.get_RequireSameOrigin()",
            "Name": "get_RequireSameOrigin",
            "KeyType": "",
            "RecommendedActions": [
                {
                    "Source": "Amazon",
                    "Preferred": "yes",
                    "TargetFrameworks": [
                        "netcoreapp3.1"
                    ],
                    "Description": "System.Web (AKA classic ASP.NET) won't be ported to .NET Core. See https://aka.ms/unsupported-netfx-api.",
                    "Actions": []
                }
            ]
        },
        {
            "Type": "Method",
            "Value": "System.Web.WebSockets.AspNetWebSocketContext.get_IsClientConnected()",
            "Name": "get_IsClientConnected",
            "KeyType": "",
            "RecommendedActions": [
                {
                    "Source": "Amazon",
                    "Preferred": "yes",
                    "TargetFrameworks": [
                        "netcoreapp3.1"
                    ],
                    "Description": "System.Web (AKA classic ASP.NET) won't be ported to .NET Core. See https://aka.ms/unsupported-netfx-api.",
                    "Actions": []
                }
            ]
        },
        {
            "Type": "Method",
            "Value": "System.Web.WebSockets.AspNetWebSocketContext.get_SecWebSocketVersion()",
            "Name": "get_SecWebSocketVersion",
            "KeyType": "",
            "RecommendedActions": [
                {
                    "Source": "Amazon",
                    "Preferred": "yes",
                    "TargetFrameworks": [
                        "netcoreapp3.1"
                    ],
                    "Description": "System.Web (AKA classic ASP.NET) won't be ported to .NET Core. See https://aka.ms/unsupported-netfx-api.",
                    "Actions": []
                }
            ]
        },
        {
            "Type": "Method",
            "Value": "System.Web.WebSockets.AspNetWebSocketContext.get_PathInfo()",
            "Name": "get_PathInfo",
            "KeyType": "",
            "RecommendedActions": [
                {
                    "Source": "Amazon",
                    "Preferred": "yes",
                    "TargetFrameworks": [
                        "netcoreapp3.1"
                    ],
                    "Description": "System.Web (AKA classic ASP.NET) won't be ported to .NET Core. See https://aka.ms/unsupported-netfx-api.",
                    "Actions": []
                }
            ]
        },
        {
            "Type": "Namespace",
            "Value": "System.Web.WebSockets",
            "Name": "System.Web.WebSockets",
            "KeyType": "",
            "RecommendedActions": [
                {
                    "Source": "Amazon",
                    "Preferred": "yes",
                    "TargetFrameworks": [
                        "netcoreapp3.1"
                    ],
                    "Description": "System.Web (AKA classic ASP.NET) won't be ported to .NET Core. See https://aka.ms/unsupported-netfx-api.",
                    "Actions": []
                }
            ]
        },
        {
            "Type": "Method",
            "Value": "System.Web.WebSockets.AspNetWebSocketContext.get_UserHostAddress()",
            "Name": "get_UserHostAddress",
            "KeyType": "",
            "RecommendedActions": [
                {
                    "Source": "Amazon",
                    "Preferred": "yes",
                    "TargetFrameworks": [
                        "netcoreapp3.1"
                    ],
                    "Description": "System.Web (AKA classic ASP.NET) won't be ported to .NET Core. See https://aka.ms/unsupported-netfx-api.",
                    "Actions": []
                }
            ]
        },
        {
            "Type": "Method",
            "Value": "System.Web.WebSockets.AspNetWebSocketContext.get_UserHostName()",
            "Name": "get_UserHostName",
            "KeyType": "",
            "RecommendedActions": [
                {
                    "Source": "Amazon",
                    "Preferred": "yes",
                    "TargetFrameworks": [
                        "netcoreapp3.1"
                    ],
                    "Description": "System.Web (AKA classic ASP.NET) won't be ported to .NET Core. See https://aka.ms/unsupported-netfx-api.",
                    "Actions": []
                }
            ]
        },
        {
            "Type": "Method",
            "Value": "System.Web.WebSockets.AspNetWebSocketOptions.set_SubProtocol(string)",
            "Name": "set_SubProtocol",
            "KeyType": "",
            "RecommendedActions": [
                {
                    "Source": "Amazon",
                    "Preferred": "yes",
                    "TargetFrameworks": [
                        "netcoreapp3.1"
                    ],
                    "Description": "System.Web (AKA classic ASP.NET) won't be ported to .NET Core. See https://aka.ms/unsupported-netfx-api.",
                    "Actions": []
                }
            ]
        }
    ]
}