{
    "Name": "System.Web.UI.WebControls.Expressions",
    "Version": "1.0.0",
    "Packages": {
        "Type": "SDK",
        "Name": "System.Web.UI.WebControls.Expressions"
    },
    "Recommendations": [
        {
            "Type": "Namespace",
            "Value": "System.Web.UI.WebControls.Expressions",
            "RecommendedActions": [
                {
                    "Source": "Amazon",
                    "referred": "yes",
                    "Versions": [
                        "netcoreapp3.1"
                    ],
                    "Description": "System.Web (AKA classic ASP.NET) won't be ported to .NET Core. See https://aka.ms/unsupported-netfx-api.",
                    "Actions": []
                }
            ]
        },
        {
            "Type": "Method",
            "Value": "System.Web.UI.WebControls.Expressions.PropertyExpression.PropertyExpression()",
            "RecommendedActions": [
                {
                    "Source": "Amazon",
                    "referred": "yes",
                    "Versions": [
                        "netcoreapp3.1"
                    ],
                    "Description": "System.Web (AKA classic ASP.NET) won't be ported to .NET Core. See https://aka.ms/unsupported-netfx-api.",
                    "Actions": []
                }
            ]
        },
        {
            "Type": "Method",
            "Value": "System.Web.UI.WebControls.Expressions.ThenBy.get_Direction()",
            "RecommendedActions": [
                {
                    "Source": "Amazon",
                    "referred": "yes",
                    "Versions": [
                        "netcoreapp3.1"
                    ],
                    "Description": "System.Web (AKA classic ASP.NET) won't be ported to .NET Core. See https://aka.ms/unsupported-netfx-api.",
                    "Actions": []
                }
            ]
        },
        {
            "Type": "Method",
            "Value": "System.Web.UI.WebControls.Expressions.SearchExpression.SearchExpression()",
            "RecommendedActions": [
                {
                    "Source": "Amazon",
                    "referred": "yes",
                    "Versions": [
                        "netcoreapp3.1"
                    ],
                    "Description": "System.Web (AKA classic ASP.NET) won't be ported to .NET Core. See https://aka.ms/unsupported-netfx-api.",
                    "Actions": []
                }
            ]
        },
        {
            "Type": "Method",
            "Value": "System.Web.UI.WebControls.Expressions.ThenBy.ThenBy()",
            "RecommendedActions": [
                {
                    "Source": "Amazon",
                    "referred": "yes",
                    "Versions": [
                        "netcoreapp3.1"
                    ],
                    "Description": "System.Web (AKA classic ASP.NET) won't be ported to .NET Core. See https://aka.ms/unsupported-netfx-api.",
                    "Actions": []
                }
            ]
        },
        {
            "Type": "Method",
            "Value": "System.Web.UI.WebControls.Expressions.DataSourceExpression.get_IsTrackingViewState()",
            "RecommendedActions": [
                {
                    "Source": "Amazon",
                    "referred": "yes",
                    "Versions": [
                        "netcoreapp3.1"
                    ],
                    "Description": "System.Web (AKA classic ASP.NET) won't be ported to .NET Core. See https://aka.ms/unsupported-netfx-api.",
                    "Actions": []
                }
            ]
        },
        {
            "Type": "Method",
            "Value": "System.Web.UI.WebControls.Expressions.RangeExpression.get_MinType()",
            "RecommendedActions": [
                {
                    "Source": "Amazon",
                    "referred": "yes",
                    "Versions": [
                        "netcoreapp3.1"
                    ],
                    "Description": "System.Web (AKA classic ASP.NET) won't be ported to .NET Core. See https://aka.ms/unsupported-netfx-api.",
                    "Actions": []
                }
            ]
        },
        {
            "Type": "Method",
            "Value": "System.Web.UI.WebControls.Expressions.ParameterDataSourceExpression.get_Parameters()",
            "RecommendedActions": [
                {
                    "Source": "Amazon",
                    "referred": "yes",
                    "Versions": [
                        "netcoreapp3.1"
                    ],
                    "Description": "System.Web (AKA classic ASP.NET) won't be ported to .NET Core. See https://aka.ms/unsupported-netfx-api.",
                    "Actions": []
                }
            ]
        },
        {
            "Type": "Method",
            "Value": "System.Web.UI.WebControls.Expressions.DataSourceExpression.SetDirty()",
            "RecommendedActions": [
                {
                    "Source": "Amazon",
                    "referred": "yes",
                    "Versions": [
                        "netcoreapp3.1"
                    ],
                    "Description": "System.Web (AKA classic ASP.NET) won't be ported to .NET Core. See https://aka.ms/unsupported-netfx-api.",
                    "Actions": []
                }
            ]
        },
        {
            "Type": "Method",
            "Value": "System.Web.UI.WebControls.Expressions.DataSourceExpression.get_DataSource()",
            "RecommendedActions": [
                {
                    "Source": "Amazon",
                    "referred": "yes",
                    "Versions": [
                        "netcoreapp3.1"
                    ],
                    "Description": "System.Web (AKA classic ASP.NET) won't be ported to .NET Core. See https://aka.ms/unsupported-netfx-api.",
                    "Actions": []
                }
            ]
        },
        {
            "Type": "Method",
            "Value": "System.Web.UI.WebControls.Expressions.OrderByExpression.get_ThenByExpressions()",
            "RecommendedActions": [
                {
                    "Source": "Amazon",
                    "referred": "yes",
                    "Versions": [
                        "netcoreapp3.1"
                    ],
                    "Description": "System.Web (AKA classic ASP.NET) won't be ported to .NET Core. See https://aka.ms/unsupported-netfx-api.",
                    "Actions": []
                }
            ]
        },
        {
            "Type": "Method",
            "Value": "System.Web.UI.WebControls.Expressions.DataSourceExpression.System.Web.UI.IStateManager.TrackViewState()",
            "RecommendedActions": [
                {
                    "Source": "Amazon",
                    "referred": "yes",
                    "Versions": [
                        "netcoreapp3.1"
                    ],
                    "Description": "System.Web (AKA classic ASP.NET) won't be ported to .NET Core. See https://aka.ms/unsupported-netfx-api.",
                    "Actions": []
                }
            ]
        },
        {
            "Type": "Method",
            "Value": "System.Web.UI.WebControls.Expressions.DataSourceExpression.System.Web.UI.IStateManager.SaveViewState()",
            "RecommendedActions": [
                {
                    "Source": "Amazon",
                    "referred": "yes",
                    "Versions": [
                        "netcoreapp3.1"
                    ],
                    "Description": "System.Web (AKA classic ASP.NET) won't be ported to .NET Core. See https://aka.ms/unsupported-netfx-api.",
                    "Actions": []
                }
            ]
        },
        {
            "Type": "Method",
            "Value": "System.Web.UI.WebControls.Expressions.OrderByExpression.get_Direction()",
            "RecommendedActions": [
                {
                    "Source": "Amazon",
                    "referred": "yes",
                    "Versions": [
                        "netcoreapp3.1"
                    ],
                    "Description": "System.Web (AKA classic ASP.NET) won't be ported to .NET Core. See https://aka.ms/unsupported-netfx-api.",
                    "Actions": []
                }
            ]
        },
        {
            "Type": "Method",
            "Value": "System.Web.UI.WebControls.Expressions.CustomExpression.CustomExpression()",
            "RecommendedActions": [
                {
                    "Source": "Amazon",
                    "referred": "yes",
                    "Versions": [
                        "netcoreapp3.1"
                    ],
                    "Description": "System.Web (AKA classic ASP.NET) won't be ported to .NET Core. See https://aka.ms/unsupported-netfx-api.",
                    "Actions": []
                }
            ]
        },
        {
            "Type": "Method",
            "Value": "System.Web.UI.WebControls.Expressions.MethodExpression.GetQueryable(System.Linq.IQueryable)",
            "RecommendedActions": [
                {
                    "Source": "Amazon",
                    "referred": "yes",
                    "Versions": [
                        "netcoreapp3.1"
                    ],
                    "Description": "System.Web (AKA classic ASP.NET) won't be ported to .NET Core. See https://aka.ms/unsupported-netfx-api.",
                    "Actions": []
                }
            ]
        },
        {
            "Type": "Method",
            "Value": "System.Web.UI.WebControls.Expressions.DataSourceExpressionCollection.RemoveAt(int)",
            "RecommendedActions": [
                {
                    "Source": "Amazon",
                    "referred": "yes",
                    "Versions": [
                        "netcoreapp3.1"
                    ],
                    "Description": "System.Web (AKA classic ASP.NET) won't be ported to .NET Core. See https://aka.ms/unsupported-netfx-api.",
                    "Actions": []
                }
            ]
        },
        {
            "Type": "Method",
            "Value": "System.Web.UI.WebControls.Expressions.CustomExpression.remove_Querying(System.EventHandler{System.Web.UI.WebControls.Expressions.CustomExpressionEventArgs})",
            "RecommendedActions": [
                {
                    "Source": "Amazon",
                    "referred": "yes",
                    "Versions": [
                        "netcoreapp3.1"
                    ],
                    "Description": "System.Web (AKA classic ASP.NET) won't be ported to .NET Core. See https://aka.ms/unsupported-netfx-api.",
                    "Actions": []
                }
            ]
        },
        {
            "Type": "Method",
            "Value": "System.Web.UI.WebControls.Expressions.RangeExpression.get_DataField()",
            "RecommendedActions": [
                {
                    "Source": "Amazon",
                    "referred": "yes",
                    "Versions": [
                        "netcoreapp3.1"
                    ],
                    "Description": "System.Web (AKA classic ASP.NET) won't be ported to .NET Core. See https://aka.ms/unsupported-netfx-api.",
                    "Actions": []
                }
            ]
        },
        {
            "Type": "Method",
            "Value": "System.Web.UI.WebControls.Expressions.SearchExpression.get_ComparisonType()",
            "RecommendedActions": [
                {
                    "Source": "Amazon",
                    "referred": "yes",
                    "Versions": [
                        "netcoreapp3.1"
                    ],
                    "Description": "System.Web (AKA classic ASP.NET) won't be ported to .NET Core. See https://aka.ms/unsupported-netfx-api.",
                    "Actions": []
                }
            ]
        },
        {
            "Type": "Method",
            "Value": "System.Web.UI.WebControls.Expressions.RangeExpression.get_MaxType()",
            "RecommendedActions": [
                {
                    "Source": "Amazon",
                    "referred": "yes",
                    "Versions": [
                        "netcoreapp3.1"
                    ],
                    "Description": "System.Web (AKA classic ASP.NET) won't be ported to .NET Core. See https://aka.ms/unsupported-netfx-api.",
                    "Actions": []
                }
            ]
        },
        {
            "Type": "Method",
            "Value": "System.Web.UI.WebControls.Expressions.ThenBy.set_Direction(System.Web.UI.WebControls.SortDirection)",
            "RecommendedActions": [
                {
                    "Source": "Amazon",
                    "referred": "yes",
                    "Versions": [
                        "netcoreapp3.1"
                    ],
                    "Description": "System.Web (AKA classic ASP.NET) won't be ported to .NET Core. See https://aka.ms/unsupported-netfx-api.",
                    "Actions": []
                }
            ]
        },
        {
            "Type": "Method",
            "Value": "System.Web.UI.WebControls.Expressions.DataSourceExpressionCollection.CopyTo(System.Web.UI.WebControls.Expressions.DataSourceExpression[], int)",
            "RecommendedActions": [
                {
                    "Source": "Amazon",
                    "referred": "yes",
                    "Versions": [
                        "netcoreapp3.1"
                    ],
                    "Description": "System.Web (AKA classic ASP.NET) won't be ported to .NET Core. See https://aka.ms/unsupported-netfx-api.",
                    "Actions": []
                }
            ]
        },
        {
            "Type": "Method",
            "Value": "System.Web.UI.WebControls.Expressions.DataSourceExpression.SetContext(System.Web.UI.Control, System.Web.HttpContext, System.Web.UI.WebControls.IQueryableDataSource)",
            "RecommendedActions": [
                {
                    "Source": "Amazon",
                    "referred": "yes",
                    "Versions": [
                        "netcoreapp3.1"
                    ],
                    "Description": "System.Web (AKA classic ASP.NET) won't be ported to .NET Core. See https://aka.ms/unsupported-netfx-api.",
                    "Actions": []
                }
            ]
        },
        {
            "Type": "Method",
            "Value": "System.Web.UI.WebControls.Expressions.DataSourceExpressionCollection.Contains(System.Web.UI.WebControls.Expressions.DataSourceExpression)",
            "RecommendedActions": [
                {
                    "Source": "Amazon",
                    "referred": "yes",
                    "Versions": [
                        "netcoreapp3.1"
                    ],
                    "Description": "System.Web (AKA classic ASP.NET) won't be ported to .NET Core. See https://aka.ms/unsupported-netfx-api.",
                    "Actions": []
                }
            ]
        },
        {
            "Type": "Method",
            "Value": "System.Web.UI.WebControls.Expressions.ParameterDataSourceExpression.SaveViewState()",
            "RecommendedActions": [
                {
                    "Source": "Amazon",
                    "referred": "yes",
                    "Versions": [
                        "netcoreapp3.1"
                    ],
                    "Description": "System.Web (AKA classic ASP.NET) won't be ported to .NET Core. See https://aka.ms/unsupported-netfx-api.",
                    "Actions": []
                }
            ]
        },
        {
            "Type": "Method",
            "Value": "System.Web.UI.WebControls.Expressions.DataSourceExpressionCollection.IndexOf(System.Web.UI.WebControls.Expressions.DataSourceExpression)",
            "RecommendedActions": [
                {
                    "Source": "Amazon",
                    "referred": "yes",
                    "Versions": [
                        "netcoreapp3.1"
                    ],
                    "Description": "System.Web (AKA classic ASP.NET) won't be ported to .NET Core. See https://aka.ms/unsupported-netfx-api.",
                    "Actions": []
                }
            ]
        },
        {
            "Type": "Method",
            "Value": "System.Web.UI.WebControls.Expressions.DataSourceExpression.System.Web.UI.IStateManager.LoadViewState(object)",
            "RecommendedActions": [
                {
                    "Source": "Amazon",
                    "referred": "yes",
                    "Versions": [
                        "netcoreapp3.1"
                    ],
                    "Description": "System.Web (AKA classic ASP.NET) won't be ported to .NET Core. See https://aka.ms/unsupported-netfx-api.",
                    "Actions": []
                }
            ]
        },
        {
            "Type": "Method",
            "Value": "System.Web.UI.WebControls.Expressions.CustomExpressionEventArgs.set_Query(System.Linq.IQueryable)",
            "RecommendedActions": [
                {
                    "Source": "Amazon",
                    "referred": "yes",
                    "Versions": [
                        "netcoreapp3.1"
                    ],
                    "Description": "System.Web (AKA classic ASP.NET) won't be ported to .NET Core. See https://aka.ms/unsupported-netfx-api.",
                    "Actions": []
                }
            ]
        },
        {
            "Type": "Method",
            "Value": "System.Web.UI.WebControls.Expressions.OfTypeExpression.GetQueryable(System.Linq.IQueryable)",
            "RecommendedActions": [
                {
                    "Source": "Amazon",
                    "referred": "yes",
                    "Versions": [
                        "netcoreapp3.1"
                    ],
                    "Description": "System.Web (AKA classic ASP.NET) won't be ported to .NET Core. See https://aka.ms/unsupported-netfx-api.",
                    "Actions": []
                }
            ]
        },
        {
            "Type": "Method",
            "Value": "System.Web.UI.WebControls.Expressions.QueryExpression.get_Expressions()",
            "RecommendedActions": [
                {
                    "Source": "Amazon",
                    "referred": "yes",
                    "Versions": [
                        "netcoreapp3.1"
                    ],
                    "Description": "System.Web (AKA classic ASP.NET) won't be ported to .NET Core. See https://aka.ms/unsupported-netfx-api.",
                    "Actions": []
                }
            ]
        },
        {
            "Type": "Method",
            "Value": "System.Web.UI.WebControls.Expressions.CustomExpressionEventArgs.get_Query()",
            "RecommendedActions": [
                {
                    "Source": "Amazon",
                    "referred": "yes",
                    "Versions": [
                        "netcoreapp3.1"
                    ],
                    "Description": "System.Web (AKA classic ASP.NET) won't be ported to .NET Core. See https://aka.ms/unsupported-netfx-api.",
                    "Actions": []
                }
            ]
        },
        {
            "Type": "Method",
            "Value": "System.Web.UI.WebControls.Expressions.DataSourceExpressionCollection.get_Context()",
            "RecommendedActions": [
                {
                    "Source": "Amazon",
                    "referred": "yes",
                    "Versions": [
                        "netcoreapp3.1"
                    ],
                    "Description": "System.Web (AKA classic ASP.NET) won't be ported to .NET Core. See https://aka.ms/unsupported-netfx-api.",
                    "Actions": []
                }
            ]
        },
        {
            "Type": "Method",
            "Value": "System.Web.UI.WebControls.Expressions.DataSourceExpression.LoadViewState(object)",
            "RecommendedActions": [
                {
                    "Source": "Amazon",
                    "referred": "yes",
                    "Versions": [
                        "netcoreapp3.1"
                    ],
                    "Description": "System.Web (AKA classic ASP.NET) won't be ported to .NET Core. See https://aka.ms/unsupported-netfx-api.",
                    "Actions": []
                }
            ]
        },
        {
            "Type": "Method",
            "Value": "System.Web.UI.WebControls.Expressions.DataSourceExpressionCollection.get_Item(int)",
            "RecommendedActions": [
                {
                    "Source": "Amazon",
                    "referred": "yes",
                    "Versions": [
                        "netcoreapp3.1"
                    ],
                    "Description": "System.Web (AKA classic ASP.NET) won't be ported to .NET Core. See https://aka.ms/unsupported-netfx-api.",
                    "Actions": []
                }
            ]
        },
        {
            "Type": "Method",
            "Value": "System.Web.UI.WebControls.Expressions.RangeExpression.set_MinType(System.Web.UI.WebControls.Expressions.RangeType)",
            "RecommendedActions": [
                {
                    "Source": "Amazon",
                    "referred": "yes",
                    "Versions": [
                        "netcoreapp3.1"
                    ],
                    "Description": "System.Web (AKA classic ASP.NET) won't be ported to .NET Core. See https://aka.ms/unsupported-netfx-api.",
                    "Actions": []
                }
            ]
        }
    ]
}